pyteomics.pepxmltk-0.3.3-py3.10-nspkg.pth
pyteomics/pepxmltk.py
pyteomics/runtandem.py
pyteomics/templates/template.jinja
pyteomics.pepxmltk-0.3.3.dist-info/LICENSE
pyteomics.pepxmltk-0.3.3.dist-info/METADATA
pyteomics.pepxmltk-0.3.3.dist-info/WHEEL
pyteomics.pepxmltk-0.3.3.dist-info/entry_points.txt
pyteomics.pepxmltk-0.3.3.dist-info/namespace_packages.txt
pyteomics.pepxmltk-0.3.3.dist-info/top_level.txt
pyteomics.pepxmltk-0.3.3.dist-info/RECORD
