Metadata-Version: 2.1
Name: pyteomics.pepxmltk
Version: 0.3.3
Summary: A utility for creation of pepXML files from Python objects and TandemXML files.
Home-page: http://hg.theorchromo.ru/pyteomics
Author: Mark Ivanov & Lev Levitsky
Author-email: pyteomics@googlegroups.com
License: License :: OSI Approved :: Apache Software License
Platform: UNKNOWN
Classifier: Intended Audience :: Science/Research
Classifier: Programming Language :: Python :: 2.7
Classifier: Programming Language :: Python :: 3
Classifier: Topic :: Education
Classifier: Topic :: Scientific/Engineering :: Bio-Informatics
Classifier: Topic :: Scientific/Engineering :: Chemistry
Classifier: Topic :: Scientific/Engineering :: Physics
Classifier: Topic :: Software Development :: Libraries
License-File: LICENSE
Requires-Dist: pyteomics[xml]
Requires-Dist: jinja2
